odoo/addons/shopinvader_restapi_invoice/README.rst
odoo/addons/shopinvader_restapi_invoice/__init__.py
odoo/addons/shopinvader_restapi_invoice/__manifest__.py
odoo/addons/shopinvader_restapi_invoice/i18n/shopinvader_invoice.pot
odoo/addons/shopinvader_restapi_invoice/i18n/shopinvader_restapi_invoice.pot
odoo/addons/shopinvader_restapi_invoice/readme/CONTRIBUTORS.rst
odoo/addons/shopinvader_restapi_invoice/readme/DESCRIPTION.rst
odoo/addons/shopinvader_restapi_invoice/services/__init__.py
odoo/addons/shopinvader_restapi_invoice/services/invoice.py
odoo/addons/shopinvader_restapi_invoice/static/description/index.html
odoo/addons/shopinvader_restapi_invoice/tests/__init__.py
odoo/addons/shopinvader_restapi_invoice/tests/common.py
odoo/addons/shopinvader_restapi_invoice/tests/test_invoice_service.py
odoo_addon_shopinvader_restapi_invoice-16.0.1.0.0.2.dist-info/METADATA
odoo_addon_shopinvader_restapi_invoice-16.0.1.0.0.2.dist-info/WHEEL
odoo_addon_shopinvader_restapi_invoice-16.0.1.0.0.2.dist-info/top_level.txt
odoo_addon_shopinvader_restapi_invoice-16.0.1.0.0.2.dist-info/RECORD
